datacorral/__init__.py
datacorral/analytics_service_object.py
datacorral/definitions.py
datacorral/google.py
datacorral-0.0.3.dist-info/LICENSE
datacorral-0.0.3.dist-info/METADATA
datacorral-0.0.3.dist-info/WHEEL
datacorral-0.0.3.dist-info/top_level.txt
datacorral-0.0.3.dist-info/RECORD
