Metadata-Version: 2.1
Name: datacorral
Version: 0.0.3
Summary: Toolkit for ETL and analysis processes
Home-page: https://github.com/sheplers/datacorral
Author: Justin Hanley
Project-URL: Bug Tracker, https://github.com/https://github.com/sheplers/datacorral/issues
Classifier: Programming Language :: Python :: 3
Classifier: License :: OSI Approved :: MIT License
Classifier: Operating System :: OS Independent
Requires-Python: >=3.6
License-File: LICENSE
Requires-Dist: pandas
Requires-Dist: httplib2
Requires-Dist: google-api-python-client
Requires-Dist: oauth2client
Requires-Dist: requests
